{
  "schema_version": "2026-03-31",
  "generated_at": "2026-04-02T00:00:00+00:00",
  "package_version": "0.9.0",
  "latest_release": "v0.9.0",
  "native_skill_count": 155,
  "curated_skill_count": 80,
  "bundle_count": 7,
  "active_category_count": 16,
  "active_categories": [
    "ai-agents",
    "backend",
    "business",
    "cli-automation",
    "communication",
    "data-ai",
    "design",
    "development",
    "devops",
    "documentation",
    "frontend",
    "fullstack-web",
    "machine-learning",
    "product",
    "testing-security",
    "tools"
  ],
  "install_client_count": 7,
  "mcp_client_count": 16,
  "mcp_config_target_count": 33,
  "mcp_config_profile_count": 20,
  "runtime_surface_count": 4,
  "runtime_surfaces": [
    {
      "id": "cli",
      "label": "CLI"
    },
    {
      "id": "api",
      "label": "API"
    },
    {
      "id": "mcp",
      "label": "MCP"
    },
    {
      "id": "a2a",
      "label": "A2A"
    }
  ],
  "validation_passed": 127,
  "validation_warn": 28,
  "validation_error": 0,
  "average_quality_score": 97.7,
  "average_best_practices_score": 99.7,
  "average_security_score": 88.0,
  "quality_score_range": {
    "min": 94,
    "max": 100
  },
  "best_practices_score_range": {
    "min": 97,
    "max": 100
  },
  "skill_level_counts": {
    "l1": 0,
    "l2": 0,
    "l3": 155
  },
  "security_status_counts": {
    "passed": 127,
    "warn": 28,
    "failed": 0
  },
  "native_intake_modes": [
    "direct-pr",
    "repository-external-intake"
  ],
  "paired_private_release_floor": "v1.0.0",
  "production_dependency_count": 8,
  "catalog_hash": "694cbd5f829bfb87c13b225e84b13bb178d2145c92de47c137b9e2364ec2c4cf",
  "generated_from": {
    "identity_path": "data/project_identity.json",
    "metadata_path": "metadata.json",
    "skills_index_path": "skills_index.json",
    "bundles_path": "data/bundles.json",
    "catalog_path": "dist/catalog.json",
    "catalog_bundles_path": "dist/bundles.json"
  }
}
